yxr_porn_core/__init__.py
yxr_porn_core/__version__.py
yxr_porn_core/py.typed
yxr_porn_core/avsox/README.md
yxr_porn_core/avsox/__init__.py
yxr_porn_core/avsox/parse_item.py
yxr_porn_core/avsox/parse_search.py
yxr_porn_core/avsox/parse_sites.py
yxr_porn_core/btdig/__init__.py
yxr_porn_core/cilisousuo/__init__.py
yxr_porn_core/cilisousuo/parse_item.py
yxr_porn_core/cilisousuo/parse_search.py
yxr_porn_core/fc2/__init__.py
yxr_porn_core/fc2/parse_item.py
yxr_porn_core/fc2ppvdb/__init__.py
yxr_porn_core/fc2ppvdb/parse_item.py
yxr_porn_core/getmag/__init__.py
yxr_porn_core/javbus/__init__.py
yxr_porn_core/javbus/parse_detail.py
yxr_porn_core/javbus/parse_list.py
yxr_porn_core/javday/__init__.py
yxr_porn_core/javday/parse_item.py
yxr_porn_core/javday/parse_search.py
yxr_porn_core/javdb/__init__.py
yxr_porn_core/javdb/parse_item.py
yxr_porn_core/javdb/parse_search.py
yxr_porn_core/javmenu/__init__.py
yxr_porn_core/javmenu/parse_code.py
yxr_porn_core/missav/__init__.py
yxr_porn_core/missav/parse_item.py
yxr_porn_core/msin/__init__.py
yxr_porn_core/msin/parse_search.py
yxr_porn_core/sukebei/__init__.py
yxr_porn_core-0.0.1.33.dist-info/METADATA
yxr_porn_core-0.0.1.33.dist-info/WHEEL
yxr_porn_core-0.0.1.33.dist-info/licenses/LICENSE
yxr_porn_core-0.0.1.33.dist-info/RECORD
