Metadata-Version: 2.4
Name: yxr-porn-core
Version: 0.0.1.33
Summary: python3.9+ library for crawling porn sites
Project-URL: Documentation, https://github.com/CroMarmot/yxr-porn-core#readme
Project-URL: Issues, https://github.com/CroMarmot/yxr-porn-core/issues
Project-URL: Source, https://github.com/CroMarmot/yxr-porn-core
Author-email: cromarmot <yexiaorain@gmail.com>
License-Expression: MIT
License-File: LICENSE
Classifier: Development Status :: 4 - Beta
Classifier: Programming Language :: Python
Classifier: Programming Language :: Python :: 3.9
Classifier: Programming Language :: Python :: 3.10
Classifier: Programming Language :: Python :: 3.11
Classifier: Programming Language :: Python :: 3.12
Classifier: Programming Language :: Python :: Implementation :: CPython
Classifier: Programming Language :: Python :: Implementation :: PyPy
Requires-Python: >=3.9
Requires-Dist: beautifulsoup4~=4.12.2
Requires-Dist: click~=8.1.3
Requires-Dist: lxml~=4.9.2
Requires-Dist: pydantic~=2.8.2
Requires-Dist: requests~=2.31.0
